magdi_data/__init__.py
magdi_data/json_helpers.py
magdi_data/data_module/__init__.py
magdi_data/data_module/abstract_data_module_3d_img.py
magdi_data/data_module/local_data_module_3d_img.py
magdi_data/data_module/minio_data_module_3d_img.py
magdi_data/data_splitting/__init__.py
magdi_data/data_splitting/abstract_data_splitter.py
magdi_data/data_splitting/local_data_splitter.py
magdi_data/data_splitting/minio_data_splitter.py
magdi_data/dataset/__init__.py
magdi_data/dataset/abstract_occ_inst_dataset_meta.py
magdi_data/dataset/nifti_occ_inst_dataset_meta.py
magdi_data/dataset/plant_nifti_occ_inst_dataset_meta.py
magdi_data-0.2.0.dist-info/METADATA
magdi_data-0.2.0.dist-info/WHEEL
magdi_data-0.2.0.dist-info/top_level.txt
magdi_data-0.2.0.dist-info/RECORD
