Metadata-Version: 2.4
Name: magdi-data
Version: 0.2.0
Summary: MAGDI data
Author-email: Christian Hänig <christian.haenig@hs-anhalt.de>, Christian Gurski <christian.gurski@hs-anhalt.de>
Project-URL: Gitlab, https://gitlab.hs-anhalt.de/ki/projekte/magdi/magdi-data
Classifier: Programming Language :: Python :: 3
Classifier: Programming Language :: Python :: 3.12
Classifier: Operating System :: OS Independent
Requires-Python: >=3.12
Requires-Dist: torch>=2.2.2
Requires-Dist: lightning>=2.5.0
Requires-Dist: numpy>=1.26.3
Requires-Dist: monai>=1.4.0
Requires-Dist: einops>=0.8.1
Requires-Dist: typing_extensions>=4.13.0
Requires-Dist: anhaltai-commons-minio>=2025.3.5
Requires-Dist: python-dotenv>=1.0.1
Requires-Dist: nibabel>=5.2.1
Requires-Dist: scikit-learn>=1.5.1
Requires-Dist: minio>=7.2.15
Requires-Dist: pydantic>=2.11.4
Requires-Dist: typing_extensions>=4.13.2
Requires-Dist: pydantic_core>=2.33.2
Requires-Dist: transformers>=4.55.2
Requires-Dist: pillow>=11.2.1
